filemeta/__init__.py
filemeta/cli.py
filemeta/database.py
filemeta/metadata_manager.py
filemeta/models.py
filemeta/utils.py
pap_filemeta-0.1.1.dist-info/METADATA
pap_filemeta-0.1.1.dist-info/WHEEL
pap_filemeta-0.1.1.dist-info/entry_points.txt
pap_filemeta-0.1.1.dist-info/top_level.txt
pap_filemeta-0.1.1.dist-info/RECORD
