Metadata-Version: 2.4
Name: PAP-filemeta
Version: 0.1.1
Summary: A CLI and API for managing server file metadata.
Home-page: https://github.com/Pranavi598/PROJECT
Author: pranavik928
Author-email: pranavik928@gmail.com
Classifier: Programming Language :: Python :: 3
Classifier: License :: OSI Approved :: MIT License
Classifier: Operating System :: OS Independent
Classifier: Topic :: System :: Filesystems
Classifier: Topic :: Utilities
Requires-Python: >=3.8
Requires-Dist: fastapi==0.111.0
Requires-Dist: uvicorn[standard]==0.29.0
Requires-Dist: sqlalchemy==2.0.30
Requires-Dist: psycopg2-binary==2.9.9
Requires-Dist: passlib==1.7.4
Requires-Dist: bcrypt==3.2.0
Requires-Dist: python-jose[cryptography]==3.3.0
Requires-Dist: python-multipart==0.0.9
Requires-Dist: pydantic==2.7.1
Requires-Dist: click==8.1.7
Dynamic: author
Dynamic: author-email
Dynamic: classifier
Dynamic: description-content-type
Dynamic: home-page
Dynamic: requires-dist
Dynamic: requires-python
Dynamic: summary
